LICENSE
MANIFEST.in
README.md
setup.cfg
setup.py
topologic/__init__.py
topologic/assertions.py
topologic/connected_components.py
topologic/exceptions.py
topologic/graph_augmentation.py
topologic/partitioned_graph.py
topologic/similarity.py
topologic.egg-info/PKG-INFO
topologic.egg-info/SOURCES.txt
topologic.egg-info/dependency_links.txt
topologic.egg-info/requires.txt
topologic.egg-info/top_level.txt
topologic/embedding/__init__.py
topologic/embedding/adjacency_spectral_embedding.py
topologic/embedding/distance.py
topologic/embedding/elbow_finder.py
topologic/embedding/embedding_container.py
topologic/embedding/embedding_methods.py
topologic/embedding/laplacian_spectral_embedding.py
topologic/embedding/node2vec_embedding.py
topologic/embedding/omnibus_embedding.py
topologic/embedding/pca.py
topologic/embedding/sample_methods.py
topologic/embedding/spectral_embedding.py
topologic/embedding/tsne.py
topologic/embedding/clustering/__init__.py
topologic/embedding/clustering/dbscan.py
topologic/embedding/clustering/gaussian_mixture_model.py
topologic/embedding/clustering/kmeans.py
topologic/embedding/clustering/wards.py
topologic/embedding/metric/__init__.py
topologic/embedding/metric/density.py
topologic/embedding/metric/distortion_metrics.py
topologic/embedding/metric/procrustes.py
topologic/io/__init__.py
topologic/io/bipartite_graph_consolidator.py
topologic/io/csv_loader.py
topologic/io/datasets.py
topologic/io/edge_detector.py
topologic/io/graph_properties.py
topologic/io/potential_edge_column_pair.py
topologic/io/tensor_projection.py
topologic/partition/__init__.py
topologic/partition/induce.py
topologic/partition/louvain_stub.py
topologic/partition/modularity.py
topologic/projection/__init__.py
topologic/projection/_common.py
topologic/projection/edge_projections.py
topologic/projection/vertex_projections.py
topologic/statistics/__init__.py
topologic/statistics/betweenness_centrality.py
topologic/statistics/defined_histogram.py
topologic/statistics/degree_centrality.py
topologic/statistics/edge_weights.py
topologic/statistics/make_cuts.py
topologic/version/__init__.py
topologic/version/version.py
